Metadata-Version: 2.1
Name: musicapi
Version: 0.3.4
Summary: QQ音乐和网易云音乐非会员歌曲的直链获取
Home-page: https://github.com/Danny-Yxzl/musicapi
Author: Yixiangzhilv
Author-email: mail@yixiangzhilv.com
Project-URL: Bug Reports, https://github.com/Danny-Yxzl/musicapi/issues
Project-URL: Say Thanks!, https://www.yixiangzhilv.com/
Project-URL: Source, https://github.com/Danny-Yxzl/musicapi
Keywords: music qq wyy
Classifier: Intended Audience :: Developers
Classifier: License :: OSI Approved :: MIT License
Classifier: Programming Language :: Python :: 3
Classifier: Programming Language :: Python :: 3.6
Classifier: Programming Language :: Python :: 3.7
Classifier: Programming Language :: Python :: 3.8
Classifier: Programming Language :: Python :: 3.9
Classifier: Programming Language :: Python :: 3.10
License-File: LICENSE
